Metadata-Version: 2.1
Name: demo-reader-program
Version: 1.0.0
Summary: Tools for reading various file formats
